LICENSE
MANIFEST.in
README.md
setup.py
genpass/genpass_cli.py
genpass/words/words-en.txt
genpassword.egg-info/PKG-INFO
genpassword.egg-info/SOURCES.txt
genpassword.egg-info/dependency_links.txt
genpassword.egg-info/entry_points.txt
genpassword.egg-info/not-zip-safe
genpassword.egg-info/top_level.txt