Metadata-Version: 1.1
Name: genpassword
Version: 1.0.1
Summary: Generate secure, random and memorable passwords of a specified length.
Home-page: https://github.com/ssrathi/genpass
Author: Shyamsunder Rathi
Author-email: shyam29@gmail.com
License: Public Domain
Keywords: password memorable
Platform: UNKNOWN
Classifier: Development Status :: 5 - Production/Stable
Classifier: Programming Language :: Python :: 2
Classifier: Environment :: Console
Classifier: Operating System :: OS Independent
Classifier: License :: Public Domain
